yinasrun/__init__.py
yinasrun-1.0.0.dist-info/entry_points.txt
yinasrun-1.0.0.dist-info/WHEEL
yinasrun-1.0.0.dist-info/METADATA
yinasrun-1.0.0.dist-info/RECORD
