Metadata-Version: 2.1
Name: yinasrun
Version: 1.0.0
Summary: 
Author: italian roast
Requires-Python: >=3.7,<4.0
Classifier: Programming Language :: Python :: 3
Classifier: Programming Language :: Python :: 3.7
Classifier: Programming Language :: Python :: 3.8
Requires-Dist: fire (>=0.3.1,<0.4.0)
